[
  {
    "name": "00.png"
  },
  {
    "name": "01.png"
  },
  {
    "name": "02.png"
  },
  {
    "name": "03.png"
  },
  {
    "name": "04.png"
  },
  {
    "name": "05.png"
  },
  {
    "name": "06.png"
  },
  {
    "name": "07.png"
  },
  {
    "name": "08.png"
  },
  {
    "name": "09.png"
  },
  {
    "name": "0a.png"
  },
  {
    "name": "0b.png"
  },
  {
    "name": "0c.png"
  },
  {
    "name": "0d.png"
  },
  {
    "name": "0e.png"
  },
  {
    "name": "0f.png"
  },
  {
    "name": "10.png"
  },
  {
    "name": "11.png"
  },
  {
    "name": "12.png"
  },
  {
    "name": "13.png"
  },
  {
    "name": "14.png"
  },
  {
    "name": "15.png"
  },
  {
    "name": "16.png"
  },
  {
    "name": "17.png"
  },
  {
    "name": "18.png"
  },
  {
    "name": "19.png"
  },
  {
    "name": "1a.png"
  },
  {
    "name": "1b.png"
  },
  {
    "name": "1c.png"
  },
  {
    "name": "1d.png"
  },
  {
    "name": "1e.png"
  },
  {
    "name": "1f.png"
  },
  {
    "name": "20.png"
  },
  {
    "name": "21.png"
  },
  {
    "name": "22.png"
  },
  {
    "name": "23.png"
  },
  {
    "name": "24.png"
  },
  {
    "name": "25.png"
  },
  {
    "name": "26.png"
  },
  {
    "name": "27.png"
  },
  {
    "name": "28.png"
  },
  {
    "name": "29.png"
  },
  {
    "name": "2a.png"
  },
  {
    "name": "2b.png"
  },
  {
    "name": "2c.png"
  },
  {
    "name": "2d.png"
  },
  {
    "name": "2e.png"
  },
  {
    "name": "2f.png"
  },
  {
    "name": "30.png"
  },
  {
    "name": "31.png"
  },
  {
    "name": "32.png"
  },
  {
    "name": "33.png"
  },
  {
    "name": "34.png"
  },
  {
    "name": "35.png"
  },
  {
    "name": "36.png"
  },
  {
    "name": "37.png"
  },
  {
    "name": "38.png"
  },
  {
    "name": "39.png"
  },
  {
    "name": "3a.png"
  },
  {
    "name": "3b.png"
  },
  {
    "name": "3c.png"
  },
  {
    "name": "3d.png"
  },
  {
    "name": "3e.png"
  },
  {
    "name": "3f.png"
  },
  {
    "name": "40.png"
  },
  {
    "name": "41.png"
  },
  {
    "name": "42.png"
  },
  {
    "name": "43.png"
  },
  {
    "name": "44.png"
  },
  {
    "name": "45.png"
  },
  {
    "name": "46.png"
  },
  {
    "name": "47.png"
  },
  {
    "name": "48.png"
  },
  {
    "name": "49.png"
  },
  {
    "name": "4a.png"
  },
  {
    "name": "4b.png"
  },
  {
    "name": "4c.png"
  },
  {
    "name": "4d.png"
  },
  {
    "name": "4e.png"
  },
  {
    "name": "4f.png"
  },
  {
    "name": "50.png"
  },
  {
    "name": "51.png"
  },
  {
    "name": "52.png"
  },
  {
    "name": "53.png"
  },
  {
    "name": "54.png"
  },
  {
    "name": "55.png"
  },
  {
    "name": "56.png"
  },
  {
    "name": "57.png"
  },
  {
    "name": "58.png"
  },
  {
    "name": "59.png"
  },
  {
    "name": "5a.png"
  },
  {
    "name": "5b.png"
  },
  {
    "name": "5c.png"
  },
  {
    "name": "5d.png"
  },
  {
    "name": "5e.png"
  },
  {
    "name": "5f.png"
  },
  {
    "name": "60.png"
  },
  {
    "name": "61.png"
  },
  {
    "name": "62.png"
  },
  {
    "name": "63.png"
  },
  {
    "name": "64.png"
  },
  {
    "name": "65.png"
  },
  {
    "name": "66.png"
  },
  {
    "name": "67.png"
  },
  {
    "name": "68.png"
  },
  {
    "name": "69.png"
  },
  {
    "name": "6a.png"
  },
  {
    "name": "6b.png"
  },
  {
    "name": "6c.png"
  },
  {
    "name": "6d.png"
  },
  {
    "name": "6e.png"
  },
  {
    "name": "6f.png"
  },
  {
    "name": "70.png"
  },
  {
    "name": "71.png"
  },
  {
    "name": "72.png"
  },
  {
    "name": "73.png"
  },
  {
    "name": "74.png"
  },
  {
    "name": "75.png"
  },
  {
    "name": "76.png"
  },
  {
    "name": "77.png"
  },
  {
    "name": "78.png"
  },
  {
    "name": "79.png"
  },
  {
    "name": "7a.png"
  },
  {
    "name": "7b.png"
  },
  {
    "name": "7c.png"
  },
  {
    "name": "7d.png"
  },
  {
    "name": "7e.png"
  },
  {
    "name": "7f.png"
  },
  {
    "name": "80.png"
  },
  {
    "name": "81.png"
  },
  {
    "name": "82.png"
  },
  {
    "name": "83.png"
  },
  {
    "name": "84.png"
  },
  {
    "name": "85.png"
  },
  {
    "name": "86.png"
  },
  {
    "name": "87.png"
  },
  {
    "name": "88.png"
  },
  {
    "name": "89.png"
  },
  {
    "name": "8a.png"
  },
  {
    "name": "8b.png"
  },
  {
    "name": "8c.png"
  },
  {
    "name": "8d.png"
  },
  {
    "name": "8e.png"
  },
  {
    "name": "8f.png"
  },
  {
    "name": "90.png"
  },
  {
    "name": "91.png"
  },
  {
    "name": "92.png"
  },
  {
    "name": "93.png"
  },
  {
    "name": "94.png"
  },
  {
    "name": "95.png"
  },
  {
    "name": "96.png"
  },
  {
    "name": "97.png"
  },
  {
    "name": "98.png"
  },
  {
    "name": "99.png"
  },
  {
    "name": "9a.png"
  },
  {
    "name": "9b.png"
  },
  {
    "name": "9c.png"
  },
  {
    "name": "9d.png"
  },
  {
    "name": "9e.png"
  },
  {
    "name": "9f.png"
  },
  {
    "name": "a0.png"
  },
  {
    "name": "a1.png"
  },
  {
    "name": "a2.png"
  },
  {
    "name": "a3.png"
  },
  {
    "name": "a4.png"
  },
  {
    "name": "a5.png"
  },
  {
    "name": "a6.png"
  },
  {
    "name": "a7.png"
  },
  {
    "name": "a8.png"
  },
  {
    "name": "a9.png"
  },
  {
    "name": "aa.png"
  },
  {
    "name": "ab.png"
  },
  {
    "name": "ac.png"
  },
  {
    "name": "ad.png"
  },
  {
    "name": "ae.png"
  },
  {
    "name": "af.png"
  }
]